cndversion/VERSION
cndversion/__init__.py
cndversion/__version__.py
cndversion/cli.py
cndversion/cnd_version.py
cndversion-2.0.2.dist-info/METADATA
cndversion-2.0.2.dist-info/WHEEL
cndversion-2.0.2.dist-info/entry_points.txt
cndversion-2.0.2.dist-info/top_level.txt
cndversion-2.0.2.dist-info/RECORD
