Metadata-Version: 2.1
Name: cndversion
Version: 2.0.2
Summary: The definitive tools to manage VERSION and change file
Home-page: https://gitlab.com/changendevops/cndversion
Author: Denis FABIEN
Author-email: denis.fabien@changendevops.com
License: MIT/X11
Project-URL: Documentation, https://changendevops.com
Project-URL: Source, https://gitlab.com/changendevops/cndversion
Classifier: License :: OSI Approved :: MIT License
Classifier: Operating System :: OS Independent
Requires-Dist: clint
Requires-Dist: coverage
